textual_canvas/__init__.py
textual_canvas/__main__.py
textual_canvas/canvas.py
textual_canvas/py.typed
textual_canvas-1.1.0.dist-info/WHEEL
textual_canvas-1.1.0.dist-info/METADATA
textual_canvas-1.1.0.dist-info/RECORD
