Metadata-Version: 2.4
Name: textual-canvas
Version: 1.1.0
Summary: A simple Textual canvas widget
Keywords: terminal,library,canvas,drawing
Author: Dave Pearson
Author-email: Dave Pearson <davep@davep.org>
License-Expression: MIT
Classifier: Environment :: Console
Classifier: Development Status :: 5 - Production/Stable
Classifier: Intended Audience :: Developers
Classifier: Operating System :: OS Independent
Classifier: Programming Language :: Python :: 3.9
Classifier: Programming Language :: Python :: 3.10
Classifier: Programming Language :: Python :: 3.11
Classifier: Programming Language :: Python :: 3.12
Classifier: Programming Language :: Python :: 3.13
Classifier: Programming Language :: Python :: 3.14
Classifier: Topic :: Terminals
Classifier: Topic :: Software Development :: Libraries
Classifier: Typing :: Typed
Requires-Dist: textual>=1.0.0
Requires-Dist: typing-extensions>=4.13.2
Requires-Python: >=3.9
Project-URL: Discussions, https://github.com/davep/textual-canvas/discussions
Project-URL: Documentation, https://textual-canvas.davep.dev/
Project-URL: Homepage, https://textual-canvas.davep.dev/
Project-URL: Issues, https://github.com/davep/textual-canvas/issues
Project-URL: Repository, https://github.com/davep/textual-canvas
Project-URL: Source, https://github.com/davep/textual-canvas
